{
  "type": "Feature",
  "stac_version": "1.0.0",
  "id": "S1_245676_IW2_20210801_20210807_VV_INT20_A085",
  "properties": {
    "data_type": "float32",
    "nodata": 0,
    "proj:shape": [
      2018,
      5410
    ],
    "proj:transform": [
      20,
      0,
      547280,
      0,
      -20,
      4909580,
      0,
      0,
      1
    ],
    "proj:epsg": 32610,
    "sar:instrument_mode": "IW",
    "sar:frequency_band": "C",
    "sar:observation_direction": "right",
    "hyp3:reference_granule": "S1_245676_IW2_20210801T141441_VV_3C1B-BURST",
    "hyp3:secondary_granule": "S1_245676_IW2_20210807T141400_VV_6C4D-BURST",
    "hyp3:reference_orbit_direction": "DESCENDING",
    "hyp3:reference_orbit_number": 39037,
    "hyp3:secondary_orbit_direction": "DESCENDING",
    "hyp3:secondary_orbit_number": 28141,
    "hyp3:baseline": -41.4002284165875,
    "hyp3:utc_time": 51265.202703,
    "hyp3:heading": -165.9916479264471,
    "hyp3:spacecraft_height": 693000.0,
    "hyp3:earth_radius_at_nadir": 6337286.638938101,
    "hyp3:slant_range_near": 846602.7096597819,
    "hyp3:slant_range_center": 876460.7072840882,
    "hyp3:slant_range_far": 906318.7049083945,
    "hyp3:range_looks": 5,
    "hyp3:azimuth_looks": 1,
    "hyp3:insar_phase_filter": true,
    "hyp3:phase_filter_parameter": 0.5,
    "hyp3:range_bandpass_filter": false,
    "hyp3:azimuth_bandpass_filter": false,
    "hyp3:dem_source": "GLO_30",
    "hyp3:dem_resolution": 30,
    "hyp3:unwrapping_type": "snaphu_mcf",
    "hyp3:speckle_filter": true,
    "hyp3:water_mask": true,
    "sar:product_type": "INSAR_ISCE_BURST",
    "sar:polarizations": [
      "VV"
    ],
    "sar:looks_azimuth": 1,
    "sar:looks_range": 5,
    "sat:orbit_state": "descending",
    "sat:absolute_orbit": 39037,
    "view:azimuth": 194.0083520735529,
    "processing:level": "L3",
    "processing:lineage": "Created by ASF DAAC HyP3 using the hyp3_gamma plugin running GAMMA SAR processing software",
    "hyp3:start_datetime": "2021-08-01T14:14:41+00:00",
    "hyp3:end_datetime": "2021-08-07T14:14:00+00:00",
    "datetime": "2021-08-04T14:14:20.500000Z"
  },
  "geometry": {
    "type": "Polygon",
    "coordinates": [
      [
        [
          -122.40690688478102,
          43.95967820950884
        ],
        [
          -121.0620466217456,
          43.95967820950884
        ],
        [
          -121.0620466217456,
          44.337946901233295
        ],
        [
          -122.40690688478102,
          44.337946901233295
        ],
        [
          -122.40690688478102,
          43.95967820950884
        ]
      ]
    ]
  },
  "links": [
    {
      "rel": "root",
      "href": "../collection.json",
      "type": "application/json",
      "title": "ASF HyP3 Products"
    },
    {
      "rel": "collection",
      "href": "../collection.json",
      "type": "application/json",
      "title": "ASF HyP3 Products"
    },
    {
      "rel": "parent",
      "href": "../collection.json",
      "type": "application/json",
      "title": "ASF HyP3 Products"
    }
  ],
  "assets": {
    "corr": {
      "href": "https://d3gm2hf49xd6jj.cloudfront.net/4c2fd78c-effb-49a7-87fc-9cebb5fd190b/S1_245676_IW2_20210801_20210807_VV_INT20_A085_corr.tif",
      "type": "image/tiff; application=geotiff",
      "roles": [
        "data"
      ]
    },
    "unw_phase": {
      "href": "https://d3gm2hf49xd6jj.cloudfront.net/4c2fd78c-effb-49a7-87fc-9cebb5fd190b/S1_245676_IW2_20210801_20210807_VV_INT20_A085_unw_phase.tif",
      "type": "image/tiff; application=geotiff",
      "roles": [
        "data"
      ]
    },
    "lv_phi": {
      "href": "https://d3gm2hf49xd6jj.cloudfront.net/4c2fd78c-effb-49a7-87fc-9cebb5fd190b/S1_245676_IW2_20210801_20210807_VV_INT20_A085_lv_phi.tif",
      "type": "image/tiff; application=geotiff",
      "roles": [
        "data"
      ]
    },
    "lv_theta": {
      "href": "https://d3gm2hf49xd6jj.cloudfront.net/4c2fd78c-effb-49a7-87fc-9cebb5fd190b/S1_245676_IW2_20210801_20210807_VV_INT20_A085_lv_theta.tif",
      "type": "image/tiff; application=geotiff",
      "roles": [
        "data"
      ]
    },
    "dem": {
      "href": "https://d3gm2hf49xd6jj.cloudfront.net/4c2fd78c-effb-49a7-87fc-9cebb5fd190b/S1_245676_IW2_20210801_20210807_VV_INT20_A085_dem.tif",
      "type": "image/tiff; application=geotiff",
      "roles": [
        "data"
      ]
    },
    "water_mask": {
      "href": "https://d3gm2hf49xd6jj.cloudfront.net/4c2fd78c-effb-49a7-87fc-9cebb5fd190b/S1_245676_IW2_20210801_20210807_VV_INT20_A085_water_mask.tif",
      "type": "image/tiff; application=geotiff",
      "roles": [
        "data"
      ]
    },
    "conncomp": {
      "href": "https://d3gm2hf49xd6jj.cloudfront.net/4c2fd78c-effb-49a7-87fc-9cebb5fd190b/S1_245676_IW2_20210801_20210807_VV_INT20_A085_conncomp.tif",
      "type": "image/tiff; application=geotiff",
      "roles": [
        "data"
      ]
    },
    "wrapped_phase": {
      "href": "https://d3gm2hf49xd6jj.cloudfront.net/4c2fd78c-effb-49a7-87fc-9cebb5fd190b/S1_245676_IW2_20210801_20210807_VV_INT20_A085_wrapped_phase.tif",
      "type": "image/tiff; application=geotiff",
      "roles": [
        "data"
      ]
    },
    "thumbnail": {
      "href": "https://d3gm2hf49xd6jj.cloudfront.net/4c2fd78c-effb-49a7-87fc-9cebb5fd190b/S1_245676_IW2_20210801_20210807_VV_INT20_A085_unw_phase.png",
      "type": "image/png",
      "roles": [
        "thumbnail"
      ]
    }
  },
  "bbox": [
    -122.40690688478102,
    43.95967820950884,
    -121.0620466217456,
    44.337946901233295
  ],
  "stac_extensions": [
    "https://stac-extensions.github.io/projection/v1.1.0/schema.json",
    "https://stac-extensions.github.io/raster/v1.1.0/schema.json",
    "https://stac-extensions.github.io/sar/v1.0.0/schema.json",
    "https://stac-extensions.github.io/sat/v1.0.0/schema.json",
    "https://stac-extensions.github.io/view/v1.0.0/schema.json"
  ],
  "collection": "hyp3_jobs"
}